rpkimancer_aspa/__init__.py
rpkimancer_aspa/conjure.py
rpkimancer_aspa/py.typed
rpkimancer_aspa/sigobj.py
rpkimancer_aspa/asn1/RPKI-ASPA-2022.asn
rpkimancer_aspa/asn1/__init__.py
rpkimancer_aspa-0.9.2.dist-info/METADATA
rpkimancer_aspa-0.9.2.dist-info/WHEEL
rpkimancer_aspa-0.9.2.dist-info/entry_points.txt
rpkimancer_aspa-0.9.2.dist-info/top_level.txt
rpkimancer_aspa-0.9.2.dist-info/RECORD
