Metadata-Version: 2.1
Name: rpkimancer-aspa
Version: 0.9.2
Summary: A rpkimancer plugin providing support for ASPA objects
Home-page: https://github.com/benmaddison/rpkimancer-aspa
Author: Ben Maddison
Author-email: benm@workonline.africa
License: MIT
Project-URL: Documentation, https://benmaddison.github.io/rpkimancer-aspa
Project-URL: Bug Tracker, https://github.com/benmaddison/rpkimancer-aspa/issues
Keywords: rpki,draft-ietf-sidrops-aspa-profile
Classifier: Development Status :: 4 - Beta
Classifier: Environment :: Console
Classifier: Intended Audience :: Developers
Classifier: Intended Audience :: Telecommunications Industry
Classifier: Natural Language :: English
Classifier: License :: OSI Approved :: MIT License
Classifier: Programming Language :: Python :: 3
Classifier: Programming Language :: Python :: 3.8
Classifier: Programming Language :: Python :: 3.9
Classifier: Programming Language :: Python :: 3.10
Classifier: Topic :: Internet
Classifier: Topic :: Security :: Cryptography
Classifier: Topic :: Software Development :: Testing
Classifier: Typing :: Typed
Requires-Python: >=3.8
Requires-Dist: rpkimancer (<0.3.0,>=0.2.0)
